emoji_ops/__init__.py
emoji_ops/__main__.py
emoji_ops-1.0.0.dist-info/LICENSE
emoji_ops-1.0.0.dist-info/METADATA
emoji_ops-1.0.0.dist-info/WHEEL
emoji_ops-1.0.0.dist-info/top_level.txt
emoji_ops-1.0.0.dist-info/zip-safe
emoji_ops-1.0.0.dist-info/RECORD
